ss3a_model/__init__.py
ss3a_model/model_utilty.py
ss3a_model/models.py
ss3a-0.0.5.dist-info/LICENSE
ss3a-0.0.5.dist-info/METADATA
ss3a-0.0.5.dist-info/WHEEL
ss3a-0.0.5.dist-info/top_level.txt
ss3a-0.0.5.dist-info/RECORD
