Metadata-Version: 2.1
Name: ss3a
Version: 0.0.5
Summary: SYLKSOFT常用工具
Home-page: https://www.sylksoft.com
Download-URL: https://pypi.org/project/ss3a/
Author: Ken Chen
Author-email: ken@sylksoft.com
License: MIT
Classifier: Programming Language :: Python :: 3.7
Classifier: Programming Language :: Python :: 3.8
Classifier: Programming Language :: Python :: 3.9
Classifier: Programming Language :: Python :: 3.10
Classifier: Programming Language :: Python :: 3.11
Requires-Python: >=3.7
License-File: LICENSE
Requires-Dist: SQLAlchemy (~=2.0.19)
Requires-Dist: setuptools (==68.0.0)
